Metadata-Version: 2.1
Name: unary-coding
Version: 1.0.5
Summary: Didactical python package implementing coding and decoding for unary and inverted unary.
Home-page: https://github.com/LucaCappelletti94/unary_coding
Author: Luca Cappelletti
Author-email: cappelletti.luca94@gmail.com
License: MIT
Platform: UNKNOWN
Classifier: Development Status :: 3 - Alpha
Classifier: License :: OSI Approved :: MIT License
Classifier: Programming Language :: Python :: 3
Provides-Extra: test
